ParticleChromo3D/Helper.py
ParticleChromo3D/Ps.py
ParticleChromo3D/Swarm.py
ParticleChromo3D/TransformVCM.py
ParticleChromo3D/__init__.py
ParticleChromo3D/particle_chromo_logger.py
ParticleChromo3D/pdbToNeo4j.py
ParticleChromo3D/runner_sp.py
tests/__init__.py
tests/test_helper.py
tests/test_pdb_to_neo4j.py
tests/test_ps_main.py
tests/test_runner_sp.py
tests/test_transform_vcm.py
particlechromo3d-1.0.3.dist-info/METADATA
particlechromo3d-1.0.3.dist-info/WHEEL
particlechromo3d-1.0.3.dist-info/top_level.txt
particlechromo3d-1.0.3.dist-info/RECORD
