Metadata-Version: 2.4
Name: ParticleChromo3D
Version: 1.0.3
Summary: 3D chromosome structure reconstruction using ParticleChromo3D+
Home-page: https://github.com/OluwadareLab/ParticleChromo3D_Plus
Author: Oluwadare Lab
Author-email: dvadnais@uccs.edu
Classifier: Programming Language :: Python :: 3
Classifier: License :: OSI Approved :: MIT License
Classifier: Operating System :: OS Independent
Requires-Python: >=3.6
Requires-Dist: requests
Requires-Dist: Biopython
Requires-Dist: scipy
Requires-Dist: numpy
Requires-Dist: secure-smtplib
Requires-Dist: neo4j
Dynamic: author
Dynamic: author-email
Dynamic: classifier
Dynamic: description
Dynamic: description-content-type
Dynamic: home-page
Dynamic: requires-dist
Dynamic: requires-python
Dynamic: summary
